setup.py
pzm/__init__.py
pzm/doc.py
pzm/hub.py
pzm/pzm.py
pzm.egg-info/PKG-INFO
pzm.egg-info/SOURCES.txt
pzm.egg-info/dependency_links.txt
pzm.egg-info/entry_points.txt
pzm.egg-info/requires.txt
pzm.egg-info/top_level.txt
tests/__init__.py
tests/test_splice.py