Metadata-Version: 1.0
Name: pzm
Version: 0.0.6
Summary: quickly splice subtitles
Home-page: https://nosoyyo.github.io
Author: nosoyyo
Author-email: oyyoson@gmail.com
License: WTFPL
Keywords: splice,movie,subtitle
Platform: any
